resubname.py
resubname-0.3.0.dist-info/entry_points.txt
resubname-0.3.0.dist-info/LICENSE
resubname-0.3.0.dist-info/WHEEL
resubname-0.3.0.dist-info/METADATA
resubname-0.3.0.dist-info/RECORD
