Metadata-Version: 2.1
Name: resubname
Version: 0.3.0
Summary: Rename subtitle filenames to match videos.
Home-page: https://github.com/whtsky/resubname
License: BSD-3-Clause
Author: Wu Haotian
Author-email: whtsky@gmail.com
Requires-Python: >=3.6,<4.0
Classifier: License :: OSI Approved :: BSD License
Classifier: Programming Language :: Python :: 3
Classifier: Programming Language :: Python :: 3.6
Classifier: Programming Language :: Python :: 3.7
Classifier: Programming Language :: Python :: 3.8
Project-URL: Repository, https://github.com/whtsky/resubname
